inidiff/cli.py
inidiff/diff.py
inidiff/__init__.py
inidiff/tests/test_diff.py
inidiff/tests/__init__.py
inidiff/tests/test_cli.py
inidiff-0.1.0.dist-info/DESCRIPTION.rst
inidiff-0.1.0.dist-info/entry_points.txt
inidiff-0.1.0.dist-info/top_level.txt
inidiff-0.1.0.dist-info/RECORD
inidiff-0.1.0.dist-info/METADATA
inidiff-0.1.0.dist-info/WHEEL
inidiff-0.1.0.dist-info/metadata.json
