Metadata-Version: 2.0
Name: inidiff
Version: 0.1.0
Summary: Find the differences between two ini config files
Home-page: https://github.com/kragniz/inidiff
Author: Louis Taylor
Author-email: louis@kragniz.eu
License: UNKNOWN
Platform: UNKNOWN
Classifier: Development Status :: 2 - Pre-Alpha
Classifier: Programming Language :: Python
Classifier: Programming Language :: Python :: 2
Classifier: Programming Language :: Python :: 2.7
Classifier: Programming Language :: Python :: 3
Classifier: Programming Language :: Python :: 3.3
Requires-Dist: six
Requires-Dist: ordered-set
